manydataapi/__init__.py
manydataapi/linkedin/__init__.py
manydataapi/linkedin/linkedin_access.py
manydataapi/velib/__init__.py
manydataapi/velib/data_jcdecaux.py
manydataapi-0.1.7.dist-info/METADATA
manydataapi-0.1.7.dist-info/RECORD
manydataapi-0.1.7.dist-info/WHEEL
manydataapi-0.1.7.dist-info/top_level.txt
