Metadata-Version: 2.1
Name: manydataapi
Version: 0.1.7
Summary: Pieces of code to access various API, most for teaching purposes.
Home-page: http://www.xavierdupre.fr/app/manydataapi/helpsphinx/index.html
Author: Xavier Dupré
Author-email: xavier.dupre@gmail.com
License: MIT
Download-URL: https://github.com/sdpython/manydataapi/
Keywords: manydataapi,ENSAE,REST,API
Platform: UNKNOWN
Classifier: Programming Language :: Python :: 3
Classifier: Intended Audience :: Developers
Classifier: Topic :: Scientific/Engineering
Classifier: Topic :: Education
Classifier: License :: OSI Approved :: MIT License
Classifier: Development Status :: 5 - Production/Stable
Provides-Extra: velib.data_velib
Provides-Extra: linkedin.linkedin_access
Requires-Dist: pyquickhelper (>=1.5.2259)
Provides-Extra: linkedin.linkedin_access
Requires-Dist: python3-linkedin; extra == 'linkedin.linkedin_access'
Provides-Extra: velib.data_velib
Requires-Dist: moviepy; extra == 'velib.data_velib'
